[
  {
    "timestamp": "2025-12-03T18:52:55.008Z",
    "sticker": "Vice Cursor",
    "stickerId": "9462",
    "collection": "2025 Community Sticker Collection Offer",
    "rarity": "blues",
    "applications": {
      "1x": 9103,
      "2x": 1207,
      "3x": 421,
      "4x": 253,
      "5x": 99
    },
    "uploadedToServer": false
  },
  {
    "timestamp": "2025-12-03T18:54:39.899Z",
    "sticker": "Sent With Love",
    "stickerId": "9460",
    "collection": "2025 Community Sticker Collection Offer",
    "rarity": "blues",
    "applications": {
      "1x": 9456,
      "2x": 1183,
      "3x": 601,
      "4x": 316,
      "5x": 137
    },
    "uploadedToServer": false
  },
  {
    "timestamp": "2025-12-03T18:56:07.368Z",
    "sticker": "Cubix Connexion",
    "stickerId": "9452",
    "collection": "2025 Community Sticker Collection Offer",
    "rarity": "blues",
    "applications": {
      "1x": 7065,
      "2x": 648,
      "3x": 336,
      "4x": 205,
      "5x": 103
    },
    "uploadedToServer": false
  },
  {
    "timestamp": "2025-12-03T18:57:18.503Z",
    "sticker": "Pop Pup",
    "stickerId": "9458",
    "collection": "2025 Community Sticker Collection Offer",
    "rarity": "blues",
    "applications": {
      "1x": 6981,
      "2x": 682,
      "3x": 388,
      "4x": 243,
      "5x": 89
    },
    "uploadedToServer": false
  },
  {
    "timestamp": "2025-12-03T18:58:31.002Z",
    "sticker": "Lock In",
    "stickerId": "9456",
    "collection": "2025 Community Sticker Collection Offer",
    "rarity": "blues",
    "applications": {
      "1x": 7900,
      "2x": 824,
      "3x": 487,
      "4x": 335,
      "5x": 141
    },
    "uploadedToServer": false
  },
  {
    "timestamp": "2025-12-03T18:59:44.626Z",
    "sticker": "Skelly Stabby",
    "stickerId": "9461",
    "collection": "2025 Community Sticker Collection Offer",
    "rarity": "blues",
    "applications": {
      "1x": 4676,
      "2x": 590,
      "3x": 310,
      "4x": 196,
      "5x": 79
    },
    "uploadedToServer": false
  },
  {
    "timestamp": "2025-12-03T19:00:57.285Z",
    "sticker": "Candy Apples",
    "stickerId": "9451",
    "collection": "2025 Community Sticker Collection Offer",
    "rarity": "blues",
    "applications": {
      "1x": 6001,
      "2x": 869,
      "3x": 454,
      "4x": 290,
      "5x": 139
    },
    "uploadedToServer": false
  },
  {
    "timestamp": "2025-12-03T19:02:10.010Z",
    "sticker": "Mimicapsule",
    "stickerId": "9457",
    "collection": "2025 Community Sticker Collection Offer",
    "rarity": "blues",
    "applications": {
      "1x": 5396,
      "2x": 552,
      "3x": 268,
      "4x": 168,
      "5x": 81
    },
    "uploadedToServer": false
  },
  {
    "timestamp": "2025-12-03T19:03:23.451Z",
    "sticker": "POTS",
    "stickerId": "9459",
    "collection": "2025 Community Sticker Collection Offer",
    "rarity": "blues",
    "applications": {
      "1x": 6470,
      "2x": 1046,
      "3x": 671,
      "4x": 449,
      "5x": 144
    },
    "uploadedToServer": false
  },
  {
    "timestamp": "2025-12-03T19:04:51.748Z",
    "sticker": "Gloves On",
    "stickerId": "9455",
    "collection": "2025 Community Sticker Collection Offer",
    "rarity": "blues",
    "applications": {
      "1x": 7229,
      "2x": 1212,
      "3x": 776,
      "4x": 528,
      "5x": 296
    },
    "uploadedToServer": false
  },
  {
    "timestamp": "2025-12-03T19:16:06.253Z",
    "sticker": "Fade Mangos",
    "stickerId": "9454",
    "collection": "2025 Community Sticker Collection Offer",
    "rarity": "blues",
    "applications": {
      "1x": 4200,
      "2x": 616,
      "3x": 280,
      "4x": 161,
      "5x": 74
    },
    "uploadedToServer": false
  }
]